xvfbwrapper.py
xvfbwrapper-0.2.18.dist-info/licenses/LICENSE
xvfbwrapper-0.2.18.dist-info/METADATA
xvfbwrapper-0.2.18.dist-info/WHEEL
xvfbwrapper-0.2.18.dist-info/top_level.txt
xvfbwrapper-0.2.18.dist-info/RECORD
