Metadata-Version: 2.4
Name: xvfbwrapper
Version: 0.2.18
Summary: Manage headless displays with Xvfb (X virtual framebuffer)
Author: Corey Goldberg
Maintainer: Corey Goldberg
License-Expression: MIT
Project-URL: homepage, https://github.com/cgoldberg/xvfbwrapper
Project-URL: source, https://github.com/cgoldberg/xvfbwrapper
Project-URL: download, https://pypi.org/project/xvfbwrapper
Keywords: Xvfb,headless,display,X11,X Window System
Classifier: Environment :: Console
Classifier: Environment :: X11 Applications
Classifier: Intended Audience :: Developers
Classifier: Intended Audience :: Information Technology
Classifier: Operating System :: POSIX
Classifier: Operating System :: POSIX :: Linux
Classifier: Operating System :: Unix
Classifier: Programming Language :: Python
Classifier: Programming Language :: Python :: 3
Classifier: Programming Language :: Python :: 3.10
Classifier: Programming Language :: Python :: 3.11
Classifier: Programming Language :: Python :: 3.12
Classifier: Programming Language :: Python :: 3.13
Classifier: Programming Language :: Python :: 3.14
Classifier: Topic :: Software Development :: Libraries :: Python Modules
Requires-Python: >=3.10
License-File: LICENSE
Dynamic: license-file
